PV_ICE/__init__.py
PV_ICE/_version.py
PV_ICE/debug_degradation.py
PV_ICE/main.py
PV_ICE/TEMP/.gitignore
PV_ICE/baselines/baseline_bifaciality_factor.csv
PV_ICE/baselines/baseline_material_energy_aluminium_frames.csv
PV_ICE/baselines/baseline_material_energy_backsheet.csv
PV_ICE/baselines/baseline_material_energy_cadmium.csv
PV_ICE/baselines/baseline_material_energy_copper.csv
PV_ICE/baselines/baseline_material_energy_encapsulant.csv
PV_ICE/baselines/baseline_material_energy_glass.csv
PV_ICE/baselines/baseline_material_energy_silicon.csv
PV_ICE/baselines/baseline_material_energy_silver.csv
PV_ICE/baselines/baseline_material_energy_tellurium.csv
PV_ICE/baselines/baseline_material_mass_WAMBACH.csv
PV_ICE/baselines/baseline_material_mass_aluminium_frames.csv
PV_ICE/baselines/baseline_material_mass_aluminium_frames_cdte.csv
PV_ICE/baselines/baseline_material_mass_backsheet.csv
PV_ICE/baselines/baseline_material_mass_cadmium.csv
PV_ICE/baselines/baseline_material_mass_copper.csv
PV_ICE/baselines/baseline_material_mass_copper_cdte.csv
PV_ICE/baselines/baseline_material_mass_encapsulant.csv
PV_ICE/baselines/baseline_material_mass_encapsulant_cdte.csv
PV_ICE/baselines/baseline_material_mass_glass.csv
PV_ICE/baselines/baseline_material_mass_glass_cdte.csv
PV_ICE/baselines/baseline_material_mass_silicon.csv
PV_ICE/baselines/baseline_material_mass_silver.csv
PV_ICE/baselines/baseline_material_mass_tellurium.csv
PV_ICE/baselines/baseline_modules_energy.csv
PV_ICE/baselines/baseline_modules_mass_US.csv
PV_ICE/baselines/baseline_modules_mass_US_CdTe.csv
PV_ICE/baselines/baseline_modules_mass_US_HistoryUtilCommOnly.csv
PV_ICE/baselines/baseline_modules_mass_US_updatedT50T90.csv
PV_ICE/baselines/baseline_modules_mass_World.csv
PV_ICE/baselines/perovskite_material_energy_glass.csv
PV_ICE/baselines/perovskite_material_mass_glass.csv
PV_ICE/baselines/perovskite_modules_energy.csv
PV_ICE/baselines/perovskite_modules_mass_US_linear.csv
PV_ICE-0.4.3.dist-info/LICENSE.md
PV_ICE-0.4.3.dist-info/METADATA
PV_ICE-0.4.3.dist-info/WHEEL
PV_ICE-0.4.3.dist-info/top_level.txt
PV_ICE-0.4.3.dist-info/RECORD
