Metadata-Version: 2.1
Name: PV_ICE
Version: 0.4.3
Summary: Tool to evaluate Circular Economy
Home-page: https://github.com/NREL/PV_ICE
Author: Silvana Ovaitt
Author-email: silvana.ovaitt@nrel.gov
License: BSD-3
Keywords: photovoltaics pv circular-economy mass-flow energy reliability
Classifier: Development Status :: 4 - Beta
Classifier: Intended Audience :: Science/Research
Classifier: License :: OSI Approved :: BSD License
Classifier: Programming Language :: Python :: 3.6
Classifier: Programming Language :: Python :: 3.7
Classifier: Programming Language :: Python :: 3.8
License-File: LICENSE.md
Requires-Dist: matplotlib
Requires-Dist: numpy
Requires-Dist: pandas
Requires-Dist: tqdm >=4.32.1
